_ferrite/__init__.py
_ferrite/_ferrite.abi3.so
ferrite-0.2.5.dist-info/METADATA
ferrite-0.2.5.dist-info/WHEEL
ferrite-0.2.5.dist-info/licenses/LICENSE
ferrite-0.2.5.dist-info/RECORD
