Metadata-Version: 2.4
Name: ferrite
Version: 0.2.5
Classifier: Development Status :: 4 - Beta
Classifier: Intended Audience :: Developers
Classifier: License :: OSI Approved :: MIT License
Classifier: Programming Language :: Rust
Classifier: Programming Language :: Python :: 3.8
Classifier: Programming Language :: Python :: 3.9
Classifier: Programming Language :: Python :: 3.10
Classifier: Programming Language :: Python :: 3.11
Classifier: Programming Language :: Python :: 3.12
Classifier: Topic :: Software Development :: Libraries :: Python Modules
Classifier: Topic :: System :: Hardware :: Hardware Drivers
Requires-Dist: eth-account>=0.8.0
License-File: LICENSE
Summary: High-performance Rust patch for Python eth-account
Author-email: Joseph Kinder <joseph.kinder70@gmail.com>
License-Expression: MIT
Requires-Python: >=3.8
Project-URL: Homepage, https://github.com/satoshiburger/ferrite
Project-URL: Repository, https://github.com/satoshiburger/ferrite
Project-URL: Documentation, https://github.com/satoshiburger/ferrite/blob/main/README.md
Project-URL: Issues, https://github.com/satoshiburger/ferrite/issues
